{
    "$schema": "./data.schema.json",
    "name": "tic-tac-toe",
    "no_of_games": 4,
    "mode": "finished",
    "mesh": [
        [
            1,
            "",
            0
        ],
        [
            "",
            1,
            0
        ],
        [
            "",
            "",
            1
        ]
    ],
    "movesHistory": [
        {
            "moveTo": "A1",
            "name": "matyo91",
            "url": "https://github.com/matyo91"
        },
        {
            "moveTo": "C2",
            "name": "AI",
            "url": "https://github.com/tanishq-singh-2301/tic-tac-toe-readme"
        },
        {
            "moveTo": "B2",
            "name": "matyo91",
            "url": "https://github.com/matyo91"
        },
        {
            "moveTo": "C1",
            "name": "AI",
            "url": "https://github.com/tanishq-singh-2301/tic-tac-toe-readme"
        },
        {
            "moveTo": "C3",
            "name": "matyo91",
            "url": "https://github.com/matyo91"
        }
    ],
    "movableMoves": [],
    "whoWon": {
        "user": "1",
        "array": [
            "A1",
            "B2",
            "C3"
        ]
    },
    "slf": ":'.':.'':"
}